dash_snap_grid/DraggableDiv.py
dash_snap_grid/Grid.py
dash_snap_grid/ResponsiveGrid.py
dash_snap_grid/__init__.py
dash_snap_grid/_imports_.py
dash_snap_grid/dash_snap_grid.min.js
dash_snap_grid/dash_snap_grid.min.js.map
dash_snap_grid/metadata.json
dash_snap_grid/package-info.json
dash_snap_grid-0.4.1.dist-info/licenses/LICENSE
dash_snap_grid-0.4.1.dist-info/METADATA
dash_snap_grid-0.4.1.dist-info/WHEEL
dash_snap_grid-0.4.1.dist-info/top_level.txt
dash_snap_grid-0.4.1.dist-info/RECORD
