Metadata-Version: 2.4
Name: dash_snap_grid
Version: 0.4.1
Summary: A draggable and resizable grid layout with responsive breakpoints, for Dash
Author: Najeem Muhammed <najeem@gmail.com>
License: MIT
Classifier: Framework :: Dash
License-File: LICENSE
Requires-Dist: dash>=3.0.0
Dynamic: author
Dynamic: classifier
Dynamic: description
Dynamic: description-content-type
Dynamic: license
Dynamic: license-file
Dynamic: requires-dist
Dynamic: summary
